ibapi/__init__.py
ibapi/account_summary_tags.py
ibapi/client.py
ibapi/client_utils.py
ibapi/comm.py
ibapi/commission_and_fees_report.py
ibapi/common.py
ibapi/connection.py
ibapi/const.py
ibapi/contract.py
ibapi/decoder.py
ibapi/decoder_utils.py
ibapi/enum_implem.py
ibapi/errors.py
ibapi/execution.py
ibapi/ibapi.pyproj
ibapi/ineligibility_reason.py
ibapi/message.py
ibapi/news.py
ibapi/object_implem.py
ibapi/order.py
ibapi/order_cancel.py
ibapi/order_condition.py
ibapi/order_state.py
ibapi/orderdecoder.py
ibapi/protobuf/AccountDataEnd_pb2.py
ibapi/protobuf/AccountDataRequest_pb2.py
ibapi/protobuf/AccountSummaryEnd_pb2.py
ibapi/protobuf/AccountSummaryRequest_pb2.py
ibapi/protobuf/AccountSummary_pb2.py
ibapi/protobuf/AccountUpdateMultiEnd_pb2.py
ibapi/protobuf/AccountUpdateMulti_pb2.py
ibapi/protobuf/AccountUpdateTime_pb2.py
ibapi/protobuf/AccountUpdatesMultiRequest_pb2.py
ibapi/protobuf/AccountValue_pb2.py
ibapi/protobuf/AllOpenOrdersRequest_pb2.py
ibapi/protobuf/AutoOpenOrdersRequest_pb2.py
ibapi/protobuf/CancelAccountSummary_pb2.py
ibapi/protobuf/CancelAccountUpdatesMulti_pb2.py
ibapi/protobuf/CancelHeadTimestamp_pb2.py
ibapi/protobuf/CancelHistogramData_pb2.py
ibapi/protobuf/CancelHistoricalData_pb2.py
ibapi/protobuf/CancelMarketData_pb2.py
ibapi/protobuf/CancelMarketDepth_pb2.py
ibapi/protobuf/CancelOrderRequest_pb2.py
ibapi/protobuf/CancelPositionsMulti_pb2.py
ibapi/protobuf/CancelPositions_pb2.py
ibapi/protobuf/CancelRealTimeBars_pb2.py
ibapi/protobuf/CancelTickByTick_pb2.py
ibapi/protobuf/ComboLeg_pb2.py
ibapi/protobuf/CompletedOrder_pb2.py
ibapi/protobuf/CompletedOrdersEnd_pb2.py
ibapi/protobuf/CompletedOrdersRequest_pb2.py
ibapi/protobuf/ContractDataEnd_pb2.py
ibapi/protobuf/ContractDataRequest_pb2.py
ibapi/protobuf/ContractData_pb2.py
ibapi/protobuf/ContractDetails_pb2.py
ibapi/protobuf/Contract_pb2.py
ibapi/protobuf/DeltaNeutralContract_pb2.py
ibapi/protobuf/ErrorMessage_pb2.py
ibapi/protobuf/ExecutionDetailsEnd_pb2.py
ibapi/protobuf/ExecutionDetails_pb2.py
pfund_ibapi-10.39.1.dist-info/WHEEL
pfund_ibapi-10.39.1.dist-info/METADATA
pfund_ibapi-10.39.1.dist-info/RECORD
