Metadata-Version: 2.3
Name: pfund-ibapi
Version: 10.39.1
Summary: Interactive Brokers TWS Python API repackaged for easy install
Author: IBG LLC, Stephen Yau
Author-email: IBG LLC <api@interactivebrokers.com>, Stephen Yau <softwareentrepreneer+pfund-ibapi@gmail.com>
License: TWS API Non-Commercial License
Classifier: Programming Language :: Python :: 3.11
Classifier: Programming Language :: Python :: 3.12
Classifier: Programming Language :: Python :: 3.13
Classifier: Programming Language :: Python :: 3.14
Requires-Dist: protobuf==5.29.3
Requires-Python: >=3.11
